caffe2/__init__.py
caffe2_for_lambda-0.0.1.dist-info/METADATA
caffe2_for_lambda-0.0.1.dist-info/WHEEL
caffe2_for_lambda-0.0.1.dist-info/top_level.txt
caffe2_for_lambda-0.0.1.dist-info/RECORD
